ultravox_client/__init__.py
ultravox_client/async_close.py
ultravox_client/audio.py
ultravox_client/patched_event_emitter.py
ultravox_client/patched_event_emitter_test.py
ultravox_client/room_listener.py
ultravox_client/session.py
ultravox_client/session_test.py
ultravox_client-0.0.9.dist-info/METADATA
ultravox_client-0.0.9.dist-info/WHEEL
ultravox_client-0.0.9.dist-info/RECORD
