Metadata-Version: 2.1
Name: ultravox-client
Version: 0.0.9
Summary: Python client SDK for Ultravox.
Home-page: https://ultravox.ai
License: Apache-2.0
Keywords: ultravox,audio,realtime,artificial intelligence
Author: Fixie Team
Author-email: hello@fixie.ai
Requires-Python: >=3.11,<4.0
Classifier: License :: OSI Approved :: Apache Software License
Classifier: Programming Language :: Python :: 3
Classifier: Programming Language :: Python :: 3.11
Classifier: Programming Language :: Python :: 3.12
Classifier: Programming Language :: Python :: 3.13
Requires-Dist: dataclasses-json (>=0.6.7,<0.7.0)
Requires-Dist: livekit (>=0.18.1,<0.19.0)
Requires-Dist: numpy (>=2.1.3,<3.0.0)
Requires-Dist: pyee (>=11.0.1,<12.0.0)
Requires-Dist: sounddevice (>=0.5.1,<0.6.0)
Requires-Dist: websockets (>=14.1,<15.0)
Project-URL: Documentation, https://fixie-ai.github.io/ultradox/
Project-URL: Repository, https://github.com/fixie-ai/ultravox-client-sdk-python
